{"cameraMode":{"drawMode":0,"name":"Shaded","section":"Shading Mode"},"sceneLighting":true,"audioPlay":false,"sceneViewState":{"m_AlwaysRefresh":false,"showFog":true,"showSkybox":true,"showFlares":true,"showImageEffects":true,"showParticleSystems":true,"showVisualEffectGraphs":true,"m_FxEnabled":true},"in2DMode":false,"pivot":{"x":0.0,"y":-0.1899999976158142,"z":-0.3899993896484375},"rotation":{"x":0.15525157749652863,"y":0.8447473645210266,"z":-0.363655149936676,"w":0.36064618825912478},"size":9.323577880859375,"orthographic":false}